LICENSE
MANIFEST.in
README.md
VERSION
requirements.txt
setup.py
docs/source/conf.py
unimatrix/__init__.py
unimatrix/conf.py
unimatrix/environ.py
unimatrix/exceptions.py
unimatrix/package.json
unimatrix.egg-info/PKG-INFO
unimatrix.egg-info/SOURCES.txt
unimatrix.egg-info/dependency_links.txt
unimatrix.egg-info/requires.txt
unimatrix.egg-info/top_level.txt
unimatrix/canon/exc/__init__.py
unimatrix/const/__init__.py
unimatrix/const/annotations.py
unimatrix/etc/__init__.py
unimatrix/etc/template.py
unimatrix/etc/tests/__init__.py
unimatrix/etc/tests/test_unit_render.py
unimatrix/ext/__init__.py
unimatrix/lib/__init__.py
unimatrix/lib/environ.py
unimatrix/lib/etc.py
unimatrix/lib/http.py
unimatrix/lib/logging.py
unimatrix/lib/meta.py
unimatrix/lib/security.py
unimatrix/lib/test.py
unimatrix/lib/timezone.py
unimatrix/lib/datastructures/__init__.py
unimatrix/lib/datastructures/dto.py
unimatrix/lib/datastructures/tests/__init__.py
unimatrix/lib/datastructures/tests/test_dto.py
unimatrix/lib/rdbms/__init__.py
unimatrix/lib/rdbms/config.py
unimatrix/lib/rdbms/tests/__init__.py
unimatrix/lib/rdbms/tests/test_load_connection.py
unimatrix/lib/rdbms/tests/test_parse_connection_env.py
unimatrix/lib/tests/__init__.py
unimatrix/lib/tests/basetestselection.py
unimatrix/lib/tests/test_test_stage_selection.py
unimatrix/lib/tests/test_unit_asynctestcase.py
unimatrix/lib/tests/test_unit_capabilities.py
unimatrix/lib/tests/test_unit_etc.py
unimatrix/lib/tests/test_unit_http_parse_qs.py
unimatrix/lib/tests/test_unit_meta_run_sync.py
unimatrix/lib/tests/test_unit_security.py
unimatrix/lib/tests/test_unit_test_scope_selection.py
unimatrix/lib/tests/test_unit_timezone.py
unimatrix/lib/wildcard/__init__.py
unimatrix/lib/wildcard/pattern.py
unimatrix/lib/wildcard/patternset.py
unimatrix/lib/wildcard/tests/__init__.py
unimatrix/lib/wildcard/tests/test_unit_wildcard.py
unimatrix/runtime/__init__.py
unimatrix/runtime/logging.py
unimatrix/runtime/settings.py
unimatrix/runtime/tests/__init__.py
unimatrix/runtime/tests/mock_boot_module.py
unimatrix/runtime/tests/test_runtime_events.py
unimatrix/runtime/tests/test_unit_boot.py
